aws_custom_json_manager/__init__.py
aws_custom_json_manager/aws_custom_json_sync_tool.py
opsworks_json-0.2.3.dist-info/DESCRIPTION.rst
opsworks_json-0.2.3.dist-info/METADATA
opsworks_json-0.2.3.dist-info/RECORD
opsworks_json-0.2.3.dist-info/WHEEL
opsworks_json-0.2.3.dist-info/entry_points.txt
opsworks_json-0.2.3.dist-info/metadata.json
opsworks_json-0.2.3.dist-info/top_level.txt
